Workbook
Name AE_Ben_All: '[1]B-IV - All Else'!$Z$42:$AS$42
Name AE_CountCost: '[1]DB - Departments'!$F$11:$H$20
Name AE_DeptList: '[1]DB - Departments'!$B$47:$B$56
Name AE_DeptList_Code: '[1]DB - Departments'!$B$47:$C$56
Name AppGrowth: '[1]DB - Cert Growth'!$M$47:$AF$47
Name Assm_HWSWCost: [1]Assumptions!$B$20
Name Assm_ImpCont: [1]Assumptions!$B$22
Name Assm_PayInc: [1]Assumptions!$B$18
Name Assm_RetBon: '[1]C-V - Other Emp Costs'!$F$47
Name Assm_SevRate: '[1]C-V - Other Emp Costs'!$G$25
Name BA_Hourly: [2]Dashboard!$C$20
Name Ben_Input: '[1]Benefit Input'!$A$10:$Y$76
Name Ben_Prob: '[1]Benefit Probabilities'!$A$10:$CL$76
Name BT_Ben_Intfc: '[1]B-II - Bus Tech'!$AO$69:$CB$69
Name BT_Ben_ModSys: '[1]B-II - Bus Tech'!$AO$73:$CB$73
Name BT_Ben_PASSuppt: '[1]B-II - Bus Tech'!$AO$67:$CB$67
Name BT_Ben_SpnCntl: '[1]B-II - Bus Tech'!$AO$75:$CB$75
Name BT_Ben_TechRat: '[1]B-II - Bus Tech'!$AO$71:$CB$71
Name BT_DeptList: '[1]DB - Departments'!$B$11:$B$21
Name BT_DeptList_Code: '[1]DB - Departments'!$B$11:$C$21
Name BUS_COST_HOUR: [3]Assumptions!$E$9
Name CertGrowth: '[1]DB - Cert Growth'!$L$10:$BT$21
Name CertGrowth_Prod: '[1]DB - Cert Growth'!$L$10:$L$21
Name CertGrowth_YrSys: '[1]DB - Cert Growth'!$L$10:$BT$10
Name ClaimsGrowth: '[1]DB - Cert Growth'!$M$77:$AF$77
Name CO_Ben_Auto: '[1]B-III - Core Ops'!$AR$131:$BK$131
Name CO_Ben_Claims: '[1]B-III - Core Ops'!$AR$135:$BK$135
Name CO_Ben_CSInt: '[1]B-III - Core Ops'!$AR$133:$BK$133
Name CO_Ben_OneSys: '[1]B-III - Core Ops'!$AR$129:$BK$129
Name CO_Ben_OutAuto: '[1]B-III - Core Ops'!$AR$137:$BK$137
Name CO_Ben_PmtMeth: '[1]B-III - Core Ops'!$AR$139:$BK$139
Name CO_Ben_SelfSvc: '[1]B-III - Core Ops'!$AR$141:$BK$141
Name CO_Ben_SpnCntrl: '[1]B-III - Core Ops'!$AR$143:$BK$143
Name CO_DeptList: '[1]DB - Departments'!$B$23:$B$45
Name CO_DeptList_Code: '[1]DB - Departments'!$B$23:$C$45
Name CONTINGENCY: [3]Assumptions!$E$84
Name Cost_Input: '[1]Cost Input'!$A$11:$Y$66
Name Cost_Prob: '[1]Cost Probabilities'!$A$10:$CL$60
Name CSC_Gap_Imp: '[1]V - CSC'!$E$96:$X$96
Name CSC_Gap_Recur: '[1]V - CSC'!$E$89:$X$89
Name CSC_OneTime: '[1]V - CSC'!$E$52:$X$52
Name CSC_Recurring: '[1]V - CSC'!$E$13:$X$13
Name Dash_Best: OFFSET('[1]Dashboard Input'!$C$9,0,0,,COUNT('[1]Dashboard Input'!$C$9:$V$9))
Name Dash_Probable: OFFSET('[1]Dashboard Input'!$C$8,0,0,,COUNT('[1]Dashboard Input'!$C$8:$V$8))
Name Dash_Submitted: OFFSET('[1]Dashboard Input'!$C$6,0,0,,COUNT('[1]Dashboard Input'!$C$6:$V$6))
Name Dash_Worst: OFFSET('[1]Dashboard Input'!$C$7,0,0,,COUNT('[1]Dashboard Input'!$C$7:$V$7))
Name DISCOUNT: [3]Assumptions!$E$7
Name Discount_Rate: [4]Dashboard!$C$10
Name DiscRate: '[5]Benefit Summary'!$D$5
Name FIN_Consult: [2]Dashboard!$C$28
Name FIN_PMO: [2]Dashboard!$C$29
Name FIN_Training: [2]Dashboard!$C$27
Name FTE_AE_Total: '[1]B-IV - All Else'!$M$42
Name FTE_BT_Efcy: '[1]B-II - Bus Tech'!$AF$67
Name FTE_BT_Suppt: '[1]B-II - Bus Tech'!$I$67
Name FTE_CO_Efcy: '[1]B-III - Core Ops'!$AF$127
Name FTE_CO_SpanCntl: '[1]B-III - Core Ops'!$AH$127
Name Group_GR: [2]Dashboard!$C$13
Name Hours_Day: [2]Dashboard!$C$30
Name Hours_Yr: [2]Dashboard!$C$25

Sheet Financial Services Cover Sheet
A2: Financial Services, Business Architecture Reference Model Version 2.0
A3: ABOUT THE BUSINESS ARCHITECTURE CONTENTS HEREIN
A4: The business architecture reference model contained herein represents a basic business architecture for a financial services institution. This reference model includes capabilities specific to a financial institution as well as commonly used strategic and supporting capabilities, a set of value streams, an information map, an organization map, and a stakeholder map. This reference model is a work-in-progress and will continue to evolve based on Guild member contributions.
A5: USAGE & DISCLAIMERS
A6: Business Architecture Guild® represents that the business architecture content contained herein: • IS DELIVERED AS-IS WITH NO CLAIM OF WARRANTY • Is to be used at one’s own risk • May be modified or augmented for use at one’s own discretion • Is not intended to fully represent a complete business architecture perspective • Does not represent any specific tool import or export format • May be updated by the Guild at any point in time to reflect evolution of the practice • Is not presented as being free from errors or omissions • IS FOR INTERNAL USE ONLY AND NOT FOR DISTRIBUTION TO 3RD PARTIES
A7: Comments should be directed to the appropriate Business Architecture Guild, reference model member forum at www.businessarchitectureguild.org.

Sheet Inventory
A1: Business Architecture Mapping Inventory
A2: Capability Map
A3: Value Stream Inventory
A4: Information Map
A5: Organization Map
A6: Stakeholder Map

Sheet Capability Map
A1: Capability Map
A2: Tier | B2: Level | C2: Capability | D2: Definition
A3: 1 | B3: 1 | C3: Brand Management | D3: Ability to establish, organize, analyze, administer, and report on all aspects of a name, symbol, or design that identifies and differentiates products, offerings, or organizational identities.
A4: 1 | B4: 2 | C4: Brand Definition | D4: Ability to articulate, establish, and create the brand in a manner which demonstrates to customers what it does, what it stands for and why it is different from its competitors.
A5: 1 | B5: 3 | C5: Brand Identity Management | D5: Ability to uniquely represent the organization in terms of the brand vision, culture, positioning, personality, relationships, and presentations of the organization.
A6: 1 | B6: 3 | C6: Brand Establishment | D6: Ability to create, form, and inculcate a brand of an organization with its target market, competitors, and the general public.
A7: 1 | B7: 2 | C7: Brand Performance Management | D7: Ability to determine how well a brand is meeting objectives or delivering against plan.
A8: 1 | B8: 3 | C8: Brand Performance Threshold Setting | D8: Ability to determine acceptable or unacceptable levels of performance.
A9: 1 | B9: 3 | C9: Brand Performance Threshold Measurement | D9: Ability to determine if a brand is exceeding or falling short of an acceptable threshold of performance.
A10: 1 | B10: 3 | C10: Brand Performance Constraints Determination | D10: Ability to assess what is causing a brand to underperform.
A11: 1 | B11: 2 | C11: Brand Loyalty Determination | D11: Ability to assess and quantify the commitment and staying power that the brand has within the markets in which it has a presence.
A12: 1 | B12: 2 | C12: Brand Awareness Determination | D12: Ability to assess and quantify the degree of familiarity and recognition a brand has within and across various markets.
A13: 1 | B13: 2 | C13: Brand Targeting | D13: Ability to identify and specify the stakeholders, markets, locations, and industry sectors marked for building brand awareness.
A14: 1 | B14: 2 | C14: Brand Matching | D14: Ability to associate a brand with other relevant aspects of the organization that are impacted by, affected, or otherwise concerned with a brand.
... A1098: 3 | B1098: 3 | C1098: Work History Management | D1098: Ability to record, evolve, and interpret changes occurring over time associated with work items, work queues, decisions, events, and other aspects of work.
A1099: Users of this template should refer to the capability mapping section of the BIZBOK® Guide. Heat mapping (effectiveness) and impact ratings are defined in BIZBOK® Guide section 3.7 that discusses performance management.

Sheet Value Streams Inventory
A1: Value Stream Inventory
A2: Value Stream Name | B2: Value Stream Definition/Description
A3: ='Acquire Asset'!$A$2 -> Acquire Asset | B3: ='Acquire Asset'!$C$2 -> The end-to-end perspective of acquiring an asset, from initiating and approving the asset request, to sourcing and processing procurement orders and delivering the asset to the requester.
A4: Acquire Servicing Portfolio | B4: The act of acquiring the servicing rights for a portfolio of loans that have been serviced by another servicer.
A5: ='Conduct Audit'!$A$2 -> Conduct Audit | B5: ='Conduct Audit'!$C$2 -> The end-to-end perspective of determining the degree to which the organization is adhering to established policies and regulations.
A6: ='Create Policy'!$A$2 -> Create Policy | B6: ='Create Policy'!C2 -> Activities involved in the end-to-end creation or update of policies that govern how the organization operates.
A7: ='Deliver Event'!$A$2 -> Deliver Meeting | B7: ='Deliver Event'!$C$2 -> The end-to-end perspective of planning and executing a meeting.
A8: ='Deliver Program'!$A$2 -> Deliver Program | B8: ='Deliver Program'!$C$2 -> The end-to-end perspective of planning and executing a program.
A9: ='Deploy Asset'!$A$2 -> Deploy Asset | B9: ='Deploy Asset'!$C$2 -> The end-to-end perspective of evaluating, building, assembling, maintaining, and readying the asset for use to fill a need within an organization.
A10: ='Develop Human Resource Career'!$A$2 -> Develop Human Resource Career | B10: ='Develop Human Resource Career'!$C$2 -> The end-to-end perspective of developing an individual's career, from performance assessment to skills and experience enhancement and individual redeployment.
A11: =+'Develop and Launch Product'!$A$2 -> Develop and Launch Product | B11: =+'Develop and Launch Product'!C2 -> Activities necessary for the introduction of a new or modified product.
A12: ='Disseminate Information'!$A$2 -> Disseminate Information | B12: ='Disseminate Information'!$C$2 -> The end-to-end perspective of requesting, creating, and delivering of information products to requester.
A13: ='Ensure Compliance'!$A$2 -> Ensure Compliance | B13: ='Ensure Compliance'!$C$2 -> The end-to-end perspective of ensuring compliance with legislation and business-driven policies, from identifying compliance requirements to implementing controls, evaluating controls effectiveness, addressing compliance incidents, and reporting compliance as required.
A14: =+'Establish Financial Agreement'!$A$2 -> Establish Financial Agreement | B14: =+'Establish Financial Agreement'!C2 -> Activities necessary for establishing a new or updating an existing agreement.
A15: ='Execute Campaign'!$A$2 -> Execute Campaign | B15: ='Execute Campaign'!$C$2 -> The end-to-end perspective of executing a campaign, from identifying the need for a campaign, to planning, designing, implementing, and measuring the effectiveness of the campaign.
A16: =+'Execute Transaction'!$A$2 -> Execute Transaction | B16: =+'Execute Transaction'!C2 -> Activities involved in completing a transaction for an agreement.
A17: =+'Resolve Issue or Inquiry'!A2 -> Resolve Issue or Inquiry | B17: =+'Resolve Issue or Inquiry'!C2 -> Activities necessary to track and resolve an issue or exception reported by a customer or other stakeholder.
A18: ='Onboard Human Resource'!$A$2 -> Onboard Human Resource | B18: ='Onboard Human Resource'!$C$2 -> The end-to-end perspective of identifying, exploring, and selecting an individual to fill a need within an organization.
A19: Onboard Partner | B19: The end-to-end perspective of identifying and commencing business with other organizations for mutual benefit.
A20: =+'Optimize Investments'!$A$2 -> Optimize Investments | B20: ='Optimize Investments'!$C$2 -> The end-to-end perspective of deciding where to make investments, based on the understanding of the enterprise's goals, strategy, current positions, and external forces.
A21: ='Report Financials'!$A$2 -> Report Financials | B21: ='Report Financials'!C2 -> The end-to-end perspective of preparing, approving, and releasing external financial statements that disclose an organization's financial status to management, investors, and the government.
A22: ='Settle Accounts'!$A$2 -> Settle Accounts | B22: ='Settle Accounts'!$C$2 -> The end-to-end perspective enabling the bi-directional exchange of payments between an organization and a customer, partner, or human resource.
A23: =+'Trade Financial Instrument'!A2 -> Trade Financial Instrument | B23: =+'Trade Financial Instrument'!C2 -> The act of executing a financial instrument trade, including clearing and settlement.
A24: Note: Value Stream names are linked to the relevant value stream templates at the end of this document.

Sheet Information Map
A1: Information Map
A2: Information Concept | B2: Information Concept Category | C2: Information Concept Definition | D2: Information Concept Types | E2: Related Information Concepts | F2: Information Concept States
A3: Brand | B3: Primary | C3: A name, symbol, or design that identifies and differentiates products, offerings, or organizational identities. | D3: Name, Symbol, Mark, Logo, Tagline, Service Mark, Jingle, Sound | E3: Market, Product, Business Entity, Intellectual Property, Policy, Channel, Partner, Campaign, Incident, Inquiry, Message | F3: Proposed, Accepted, Retired
A4: Business Entity | B4: Primary | C4: A legal body or bodies that comprises or comprise a single organization. | D4: For-Profit, Not-for-Profit, Fior-Benefit, Corporation, Partnership, Sole Proprietorship, and Government Organizations | E4: Investment, Job, Asset, Brand, Incident, Inquiry, Market, Message, Financial Forecast | F4: Extant, Non-Extant, Temporary, In-Formation
A5: Campaign | B5: Primary | C5: An outreach activity that targets a specific population, for example, customers, human resources, partners, and patients, to achieve a certain goal, such as marketing awareness, hiring activities, and health awareness. | D5: Internal, External | E5: Product, Market, Location, Brand, Meeting, Finance, Intellectual Property, Job, Location, Plan, Policy, Program, Strategy, Training, Customer, Channel | F5: Planned, Designed, Launched, In-Process, Completed, Terminated
A6: Intellectual Property | B6: Primary | C6: Intangible assets that are inventions, patents, trademarks, trade secrets, copyrights, and know-how. | D6: Idea, Authored Item, Secret, Source Identifier | E6: Business Entity, Product, Brand, Campaign, Legal Proceeding | F6: Developing (Pending), Completed
A7: Investment | B7: Primary | C7: Any type of monetary asset purchased with the idea that the asset will provide income in the future or will be sold at a higher price for a profit. | D7: Financial Instrument, Property | E7: Strategy, Plan, Asset, Payment, Policy, Research | F7: Pending/Planned/Considered, Purchased/Acquired, Sold/Matured/Expired
A8: Market | B8: Primary | C8: Individuals, populations of individuals, or organizations constituting the demand for existing or future products and services. | D8: Regional, Conceptual, Locational, Non-Locational | E8: Brand, Location, Campaign, Customer, Event, Product | F8: Latent, Explicit
A9: Message | B9: Primary | C9: A verbal, written, recorded, or digitally-represented communication, including missives, notifications, alerts, and other internally or externally targeted communication about the organization's mission, products, plans, activities, and other focal points. | D9: Internal (Inbound), External (Outbound) | E9: Asset, Brand, Event, Human Resource, Inquiry, Legal Proceeding, Policy, Program, Strategy. Work, Agreement, Customer, Channel, Partner, Product, Financial Account, Financial Transaction | F9: Pending, Completed
A10: Policy | B10: Primary | C10: A course or principle of action adopted or proposed by an organization. | D10: Formal, Informal, Temporary, Permanent | E10: Policy, Location, Authored Item | F10: Draft, Proposed, Adopted, Rescinded
A11: Plan | B11: Primary | C11: An articulated direction, related work items, and priorities to further the organization's goals and objectives across organizational units and entities within or outside the organization. | D11: Strategic, Tactical, Operational | E11: Asset, Investment, Policy, Program, Strategy, Training, Campaign, Competency, Customer, Event, Facility, Human Resource, Job, Product | F11: Pending, Initiated, Completed, Terminated
A12: Research | B12: Primary | C12: A systematic investigation into materials and sources to gather information. | D12: Primary, Secondary, Qualitative, Quantitative | E12: Program, Product, Human Resource, Inquiry, Investment, Job, Legal Proceeding, Strategy, Market | F12: Planned, Ongoing, Concluded
A13: Strategy | B13: Primary | C13: The pattern or plan that integrates an organization’s major goals, policies, and action sequences into a cohesive whole. | D13: Product, Market, Operation | E13: Strategy, Research, Market, Policy | F13: Planned, Ongoing, Concluded
... A15: Objective | B15: Secondary | C15: A quantitative, measurable result that defines strategy. | D15: Financial, Operational, Organizational, Cultural | E15: Objective, Action Item | F15: Pending, Defined, Abandoned
A16: Action Item | B16: Secondary | C16: A specific course to be taken to achieve an objective. | D16: Financial, Operational, Organizational, Cultural | F16: Proposed, Pending, Initiated, Closed, Rejected
A17: Vision | B17: Secondary | C17: The purpose of the organization. | D17: [to be further contextualized by the Business verticals as needed] | E17: Goal | F17: Pending, Defined, Abandoned
A18: Agreement | B18: Primary | C18: A set of legally binding rights and obligations created by two or more legal entities. | D18: Bilateral, Unilateral, Express, Implied, Executed, Executory, Aleatory | E18: Customer, Partner, Product, Asset, Policy, Order, Agreement, Financial Account, Payment, Facility, Channel, Conveyor, Network, Tax | F18: Pending, In Force, Terminated, Abandoned
A19: Agreement Term | B19: Secondary | C19: A legally enforceable condition set forth within the bounds of an agreement. | D19: Condition, Warranty, Innominate | E19: Policy, Time, Location | F19: Pending, In Force, Terminated, Abandoned
A20: Channel | B20: Primary | C20: A digital, analog, or physical conduit through which products, related services, or communications are delivered or received, including the Internet, phone, delivery service, satellite, radio, or physical means. | D20: Digital, Analog, Physical | E20: Partner, Policy, Product, Asset, Facility, Location | F20: Pending, Active, Retired
A21: Customer | B21: Primary | C21: A legal entity that has, plans to have, or has had an agreement with the organization, or is a recipient or beneficiary of the organization's products or services. | D21: Individual, Organization | E21: Strategy, Plan, Program, Market, Product, Customer, Partner, Human Resource, Channel, Location, Policy | F21: Potential, Actual, Past
A22: Partner | B22: Primary | C22: A legal entity that has, plans to have, or has had some degree of involvement with the organization. | D22: Supply, Distribution, Support | E22: Strategy, Plan, Program, Market, Product, Partner, Human Resource, Channel, Location | F22: Potential, Actual, Past
A23: Product | B23: Primary | C23: The overall experience provided by the combination of goods and services to satisfy the customer's needs. | D23: Good, Service | E23: Product, Asset, Location | F23: Planned, Offered, Discontinued
A24: Financial Instrument | B24: Primary | C24: A tradable asset, such as stocks, bonds, bills of exchange, futures, options, evidence of ownership, and cash. | D24: Stock, Bond, Bill of Exchange, Future, Option, Evidence of Ownership, Cash | E24: Financial Instrument, Market | F24: Pending, Issued, Matured/Expired
A25: Order | B25: Primary | C25: A request by one party to another to buy, sell, or exchange financial instruments or other goods or services. | D25: Buy, Sell, Exchange | E25: Agreement, Customer, Financial Transaction, Financial Instrument, Information, Partner, Product | F25: Pending, Executed, Expired, Cancelled
A26: Investment | B26: Primary | C26: Any type of monetary asset purchased with the idea that the asset will provide income in the future or will be sold at a higher price for a profit. | D26: Financial Instrument, Property | E26: Agreement, Financial Account, Monetary Amount, Strategy, Plan, Asset, Payment, Policy, Research | F26: Pending/Planned/Considered, Purchased/Acquired, Sold/Matured/Expired
A27: Collateral | B27: Primary | C27: Property or other asset that a customer offers as security to a borrowing or lending agreement. | D27: Real-Estate, Financial Instrument, Property | E27: Agreement, Financial Account, Monetary Amount | F27: Vested, Secured, Pledged, Accepted
A28: Finance | B28: Primary | C28: Monetary aspects and resources. | E28: Strategy, Policy
A29: Currency | B29: Secondary | C29: An agreed medium of value exchange. | D29: Representational Intrinsic (for example, CAD, USD, GBP) | E29: Investment, Financial Account, Monetary Amount | F29: Historical (Retired), Current (In-Use), Future/Intended/Planned
A30: Financial Account | B30: Secondary | C30: A named container of monetary value transactions that are typically organized into assets, liabilities, income, expense, equity, and other related categories. | D30: Asset, Liability, Income, Expense, Equity/Capital (Suspense) | E30: Policy, Financial Account, Partner, Location, Business Entity | F30: Pending, Open/Current, Closed, Suspended/Frozen
A31: Financial Forecast | B31: Secondary | C31: A prediction of a future financial aspect of the organization. | D31: Straight-Line, Moving Average, Linear Regression, Multiple Linear Regression | F31: Current, Historical, Being-Prepared, Prepared/Completed
A32: Financial Transaction | B32: Secondary | C32: An instance of a monetary amount movement or related exchange across businesses, agreements, or financial accounts. | D32: Sale, Purchase, Receipt, Payment, Deposit, Withdrawal | E32: Agreement, Financial Account, Payment, Monetary Amount, Order, Investment, Channel, Customer, Partner, Asset | F32: Historical/Executed, Pending/Current, Rejected, Cancelled
A33: Monetary Amount | B33: Secondary | C33: A representation of value as expressed in a given currency. | D33: Negative, Positive, Zero | E33: Financial Transaction, Financial Account, Payment, Currency, Tax | F33: Determined/Actual/Known, Estimated, Undetermined/Unknown
A34: Payment | B34: Secondary | C34: An obligation to remit or receive a monetary amount between an organization and a customer, partner, or other external party. | D34: Inbound, Outbound | F34: Paid (Received), Unpaid (Not Received), Cancelled, In-Flight
A35: Tax | B35: Secondary | C35: A compulsory contribution of monetary value to governing bodies. | D35: Income, Sales, Property | F35: Historical (Retired), Current (In-Use), Enforced, Future Planned, Assessed/Levied, Paid/Deducted
A36: Asset | B36: Primary | C36: Tangible or intangible property. | D36: Tangible, Intangible | E36: Agreement, Business Entity, Customer, Event, Facility, Incident, Inquiry, Investment, Job, Location, Message, Partner, Plan, Product, Program | F36: Requested, In-Preparation, In-Use, Retired, Disposed
A37: Competency | B37: Primary | C37: The skills and knowledge necessary to do something. | D37: Learned, Intrinsic | E37: Plan, Training, Competency, Policy | F37: Identified, Developing, Achieved, Dated
A38: Meeting | B38: Primary | C38: A gathering of two or more persons at a determinable time and place, including physical and virtual meetings, conferences, or related gatherings. | D38: Internal, External | E38: Asset, Campaign, Customer, Facility, Human Resource, Incident, Inquiry, Location, Market, Message, Partner, Plan, Product, Program, Schedule, Strategy, Training | F38: Planned, In-Progress, Past
A39: Facility | B39: Primary | C39: A physical structure at a given place where business is conducted. | D39: Manufacturing, Office, Storage, Services, Sales | E39: Agreement, Asset, Event, Human Resource, Location, Plan, Policy | F39: In-Service, Not-in-Service
A40: Human Resource | B40: Primary | C40: An individual who has, plans to have, or has had a legal agreement with the organization, which includes compensation and other benefits, on a temporary or permanent basis. | D40: Contractor, Employee | E40: Competency, Customer, Event, Facility, Incident, Inquiry, Job, Legal Proceeding, Location, Message, Partner, Payment, Plan, Policy, Program, Research, Work Item | F40: Former, Current, Future
A41: Incident | B41: Primary | C41: An issue involving an organization's assets, products, or operations. | D41: Critical/Severe, Emergency, Major, Minor | E41: Agreement, Asset, Brand, Channel, Customer, Event, Financial Transaction, Human Resource, Inquiry, Legal Proceeding, Message, Partner, Policy, Product, Program, Strategy, Work | F41: Imminent, Ongoing, Past
A42: Inquiry | B42: Primary | C42: A question, request, feedback, or comment that may exist inside or outside of the business, which can be received, identified, harvested, disseminated, classified, and tracked. | D42: Question, Feedback, Request | E42: Agreement, Asset, Brand, Channel, Customer, Event, Financial Account, Financial Transaction, Human Resource, Incident, Message, Partner, Policy, Product, Program, Research, Strategy, Work | F42: Current, Resolved
A43: Job | B43: Primary | C43: A named category of accountabilities, whether remunerative or non-remunerative, associated with an assigned, specific, and accountable business duty, role, or function that can be executed by a human or non-human resource. | D43: Permanent, Temporary | E43: Agreement, Asset, Business Entity, Campaign, Competency, Human Resource, Plan, Policy, Research, Strategy | F43: Open, Closed
A44: Legal Proceeding | B44: Primary | C44: An activity invoking the power of a tribunal to enforce a law. | D44: Civil, Criminal, Administrative | E44: Agreement, Customer, Decision, Human Resource, Incident, Information, Intellectual Property, Message, Partner, Policy, Research, Strategy | F44: Pending, Ongoing, Past
A45: Location | B45: Primary | C45: A position or site. | D45: Point, Area, Space | E45: Asset, Campaign, Channel, Customer, Event, Facility, Human Resource, Location, Market, Partner, Policy | F45: Known, Unknown
A46: Program | B46: Primary | C46: A coordinated collection of temporary endeavors undertaken to create a unique outcome. | D46: Strategic, Tactical, Operational | E46: Asset, Campaign, Customer, Event, Financial Account, Human Resource, Incident, Inquiry, Investment, Message, Partner, Plan, Policy, Research, Schedule, Strategy, Training | F46: Proposed, In-Flight, Paused, Completed, Cancelled
A47: Training | B47: Primary | C47: The structured content and knowledge in consumable format, associated with a curriculum, a course, workshop, seminar, or related content. | D47: Course, Curriculum, Seminar, Workshop | E47: Business Entity, Event, Facility, Human Resource, Location, Schedule | F47: Preparatory, Ongoing, Completed
A48: Work | B48: Primary | C48: Tasks, inbound requests, schedules, time, work events, and related decisions.
A49: Work Item | B49: Secondary | C49: A defined, well-bounded task that may be assigned to a stakeholder or corresponding asset. | D49: Mental, Physical | E49: Competency, Human Resource, Work Queue, Channel, Submission, Event, Job, Asset, Policy | F49: Open, In-Progress, Completed
A50: Work Queue | B50: Secondary | C50: Tasks to be processed by an individual or an automated system. | D50: Independent, Dependent | E50: Human Resource | F50: Open, In-Progress, Completed
A51: Decision | B51: Secondary | C51: A conclusion or resolution reached after considering alternative options. | D51: Binding, Provisional | E51: Decision, Location, Time | F51: Under-Deliberation, Determined
A52: Authored Item | B52: Secondary | C52: Formal written content that include reports, letters, emails, memos, and other forms of structured and unstructured text that target customers, partners, and other external and internal stakeholders. | D52: Structured, Unstructured | E52: Authored Item, Location, Time | F52: In-Development, Developed
A53: Event | B53: Secondary | C53: A situation or an occurrence. | D53: Planned, Unplanned | E53: Time, Location, Action Item | F53: Past, In-Progress, Future
A54: Submission | B54: Secondary | C54: Inbound requests, communications, and other content. | D54: Solicited, Unsolicited | E54: Message, Payment, Authored Item | F54: Incomplete, Complete
A55: Schedule | B55: Secondary | C55: An aggregation of times, dates, and milestones. | D55: Public, Private | F55: In-Development, Developed
A56: Time | B56: Secondary | C56: The indefinite continued progress of existence and events in the past, present, and future regarded as a whole in relation to work being performed. | D56: Duration, Elapsed Time, Persistence | F56: Historical, Current, Projected
A58: NOTE: Where a cell is blank in this information map, it means that a relationship or other aspect of the information concept was not defined.

Sheet Organization Map
A1: Organization Map
A2: Business Unit Level | B2: Business Unit | C2: Business Unit Type | D2: Definition
A3: 0 | B3: Financial Services Enterprise | C3: Enterprise | D3: Delivers comprehensive financial services to consumers and businesses.
A4: 1 | B4: Bank Segments | C4: Business unit | D4: Encompasses the various areas in which customers can interact with a Financial Services Organization.
A5: 2 | B5: Retail/Personal Banking | C5: Business unit | D5: Handles the administering of products and services to individual consumers.
A6: 3 | B6: Sales and Operations | C6: Business unit | D6: Handles client relationship management and the processing of a product lifecycle from initiation of an application through funding.
A7: 3 | B7: Credit Office | C7: Business unit | D7: Handles the decisioning of credit product offerings to an organization's client.
A8: 3 | B8: Product Office | C8: Business unit | D8: Handles the development and enhancement of the channel's product offerings.
A9: 3 | B9: Portfolio Management | C9: Business unit | D9: Supports the objectives regarding investment mix and policy, including balancing risk against performance.
A10: 3 | B10: Support Services | C10: Business unit | D10: Handles the back-office support of a channel including call centers, mail centers, systems support, and process support.
A11: 2 | B11: Commercial/Wholesale Banking | C11: Business unit | D11: Handles the administering of products and services to commercial clients, businesses, and business owners.
A12: 3 | B12: Sales and Operations | C12: Business unit | D12: Handles client relationship management and the processing of a product lifecycle from initiation of an application through funding.
A13: 3 | B13: Credit Office | C13: Business unit | D13: Handles the decisioning of credit product offerings to an organization's client.
A14: 3 | B14: Product Office | C14: Business unit | D14: Handles the development and enhancement of the channel's product offerings.
... A56: 2 | B56: Technology and Operations Services | C56: Partner | D56: Handles the processes and services that are both provisioned by an IT staff to their internal or external clients and used by themselves to run themselves as a business.

Sheet Stakeholder Map
A1: Stakeholder Mapping Template
A2: Stakeholder Type | B2: Stakeholder Category | C2: Stakeholder | D2: Description
A3: Internal | B3: Human Resource | C3: Account Manager | D3: An Account Manager is a person who is responsible for the management of a collection of customer or client relationships, typically focusing on customer and client acquisition and retention strategies.
A4: Internal | B4: Human Resource | C4: Authorized Representative | D4: An Authorized Representative is a person who has the authority to establish a new agreement and ensure it complies with company policy.
A5: External | B5: Partner | C5: Broker-Dealer | D5: A Broker-Dealer is a brokerage firm that buys and sells securities on its own agreement as a principal before selling the securities to customers.
A6: Internal | B6: Human Resource | C6: Channel Manager | D6: A Channel Manager is a person who manages the operations, including the production and supply of a channel of distribution.
A7: Internal or External | B7: Human Resource, Partner | C7: Collateral Appraiser | D7: A Collateral Appraiser is a licensed or certified appraiser who provides a valuation for collateral used to secure a loan.
A8: Internal | B8: Human Resource | C8: Communications Consultant | D8: A Communications Consultant is a person who provides advice and participates in the development of communication plans and strategies, messaging, and associated media.
A9: Internal | B9: Human Resource | C9: Compliance/Risk Officer | D9: A Compliance or Risk Officer is a person tasked with assessing and mitigating significant competitive, regulatory, and technological threats to an enterprise’s capital and earnings.
A10: Internal | B10: Human Resource | C10: Auditor | D10: An individual that gathers, reviews, analyzes, and reports on the financial, legal, or other records of the organization, on behalf of the organization.
A11: External | B11: Partner | C11: Credit Agency | D11: A Credit Agency is a company that collects payment history and information related to credit ratings of individuals as well as provides this service to financial institutions for credit evaluation.
A12: Internal | B12: Human Resource | C12: Credit Risk Analyst | D12: A Credit Risk Analyst is a person who evaluates the credit risks of a transaction and determines whether credit should be extended to the requesting party.
A13: External | B13: Customer | C13: Financial Account Holder | D13: A Financial Account Holder is an individual or legal entity who has, plans to have, or had an agreement in place for a savings, checking, or related financial account.
... A37: Internal | B37: Human Resource | C37: Risk Officer | D37: A Risk Officer is a person responsible for identifying, analyzing, and mitigating internal and external events that could threaten a company.
A38: External | B38: Partner | C38: Security Trader | D38: A Security Trading Organization is an organization involved in trading, market-making, and subsequent operations. | E38: Security Trader (column C) or Security Trading Organization (column D)?
A39: External | B39: Partner | C39: Stock Exchange Broker | D39: A Stock Exchange Broker is a regulated professional who executes buy and sell orders for stocks and other securities through a stock market (or over the counter) for a fee or commission.
A40: Internal or External | B40: Human Resource | C40: Strategist | D40: A Strategist is responsible for evaluating both the internal and external environment and providing advice to an organization to help achieve their strategic business priorities.
A41: Internal | B41: Human Resource | C41: Trading Specialist | D41: A Trading Specialist is a member of a stock exchange who places the trade with the Market Maker to facilitate the trading of a given stock.
A42: Internal or External | B42: Human Resource, Partner | C42: Trainer | D42: A Trainer is a person who acquires in-depth skills and knowledge in order to train an organization’s workers.
A43: External | B43: Partner | C43: Trust Bank (Custodian) | D43: A Trust Bank (Custodian) is a legal entity that acts as a fiduciary, agent, or trustee on behalf of a person or business entity for the purpose of administration, management, and the eventual transfer of assets to a beneficial party.
A44: When using this template, refer to the stakeholder mapping guidelines in the BIZBOK® Guide. The sources of each cell are noted in the note at the bottom of the cell.

Sheet Establish Financial Agreement
A1: Value Stream | B1: Value Stream Stage | C1: Description | D1: Value Proposition | E1: Entrance Criteria | F1: Exit Criteria | G1: Value Item | H1: Stakeholder(s)
A2: Establish Financial Agreement | C2: Activities necessary for establishing a new or updating an existing agreement. | D2: Customer or other requester has new or updated agreement. | H2: Customer, Partner
B3: Initiate Request | C3: The act of receiving a request or responding to an offer of expressed interest in creating or updating an agreement and verifying the requester’s identity. | E3: Expressed interest to establish or update an agreement | F3: Identified requester with validated request | G3: Request initiated, acknowledged, and accepted. | H3: Customer Service Advisor, Customer, Partner
B4: Identify Needs | C4: The act of assessing the needs of the customer in order to recommend the agreement. | E4: Identified requester with unidentified needs | F4: Identified requester with identified needs and identified agreement type | G4: Needs communicated and understood. | H4: Customer Service Advisor, Customer, Financial Planner, Product Specialist, Partner
B5: Collect Approval and Submission | C5: The act of receiving the requester’s approval to proceed as well as gathering and validating all remaining information needed to establish or modify an agreement. | E5: Identified agreement type and needs | F5: Information needed to establish or update agreement available | G5: Information needed to establish or update agreement accepted. | H5: Customer Service Advisor, Customer
B6: Evaluate Risk | C6: The act of both parties (the requester and the business) assessing the risk of establishing or updating the agreement and agreeing to proceed. | E6: All information necessary to establish the agreement available | F6: Parties agree on and accept the risks of establishing or updating an agreement | G6: Risks to proceed are acceptable. | H6: Customer Service Advisor, Risk Officer, Customer, Partner
B7: Activate Agreement | C7: The act of activating the requester’s agreement. | E7: Parties agree on and accept the risks of establishing or updating an agreement | F7: Agreement activated or updated | G7: Agreement is activated and current. | H7: Customer Service Advisor, Partner
B8: Perform Post-activation Activities | C8: The act of performing any post-activation activities such as notifications, compliance verification, or quality assurance checks. | E8: Activated and current agreement slated for finalization | F8: Essential agreement finalization activities completed | G8: Agreement activation activities and notifications finalized. | H8: Customer, Customer Service Advisor, Channel Manager, Partner

Sheet Develop and Launch Product
A1: Value Stream | B1: Value Stream Stage | C1: Description | D1: Value Proposition | E1: Entrance Criteria | F1: Exit Criteria | G1: Value Item | H1: Stakeholder(s)
A2: Develop and Launch Product | C2: Activities necessary for the introduction of a new or modified product. | D2: New or modified product introduced to market. | H2: Product Manager
B3: Conceptualize Product | C3: The act of envisioning and articulating a new or modified product based on market research, competitive analysis, customer input, and other insights. | E3: Business strategy or plan with an expressed need or idea for a product | F3: Product concept defined in accordance with business strategy | G3: Product concept ready for test marketing. | H3: Product Manager, Product Owner, Customer
B4: Market Test Product Concept | C4: The act of test marketing a product concept and establishing appropriate pricing and profitability models. | E4: Product concept defined | F4: Decision to proceed with product launch | G4: Product concept is viable and profitable. | H4: Product Manager, Delivery Channel Owner(s), Project/Program Manager, Marketing Manager, Financial Controller
B5: Design and Create Product | C5: The act of designing and creating the product and everything required to support it. | E5: Decision to proceed with product launch | F5: Product ready for launch | G5: Product created and ready for deployment. | H5: Product Manager, Delivery Channel Owner(s), Project/Program Manager, Marketing Manager
B6: Pilot Product | C6: The act of performing an initial small deployment of the product in order to mitigate risk, test, and verify. | E6: A product ready for launch | F6: “Piloted” product with a decision to proceed to full deployment | G6: Product and product distribution tested and verified. | H6: Product Manager, Delivery Channel Owner, Project/Program Manager, Marketing Manager, Financial Controller
B7: Deploy Product | C7: The act of correcting any product deficiencies that were identified in the pilot deployment and fully deploying the product to all applicable delivery channels. | E7: “Piloted” product with a decision to proceed to full deployment | F7: A successful, fully launched product | G7: Product fully deployed. | H7: Product Manager, Delivery Channel Owner, Project/Program Manager, Marketing Manager
B8: Assess Product Launch Success | C8: The act of verifying and assessing the performance of the product launch. | E8: Successful, fully launched product | F8: Qualitative and quantitative product metrics | G8: Quality of product launch rating | H8: Product Manager, Delivery Channel Owner, Project/Program Manager, Marketing Manager, Financial Controller

Sheet Execute Transaction
A1: Value Stream | B1: Value Stream Stage | C1: Description | D1: Value Proposition | E1: Entrance Criteria | F1: Exit Criteria | G1: Value Item | H1: Stakeholder(s)
A2: Execute Transaction | C2: Activities involved in completing a transaction for an agreement. | D2: Requested transaction correctly and efficiently executed on an agreement. | H2: Customer, Partner, Authorized Representative, Internal Stakeholder
B3: Initiate Transaction | C3: The act of requesting financial activity on an agreement. | E3: Request received to make a transaction | F3: Request accepted | G3: Requested transaction is being processed. | H3: Customer, Partner, Authorized Representative, Customer Service Advisor, Internal Stakeholder
B4: Validate Transaction Request | C4: The act of ensuring that the requester has authority to request the transaction and the agreement is in a valid state to allow the transaction to occur. | E4: Request received | F4: Request validated for processing | G4: Requested transaction is validated and able to proceed. | H4: Customer Service Advisor, Account Manager
B5: Identify Related Impacts | C5: The act of identifying all related effects of the transaction, including, for example, fees and charges. | E5: Request validated for processing | F5: Transaction impacts identified | G5: Related transaction impacts are identified. | H5: Product Manager, Account Manager
B6: Perform Transaction | C6: The act of applying request changes to the agreement balance and calculating the new agreement balance. | E6: Transaction impacts identified | F6: Transaction performed | G6: Requested transaction is performed. | H6: Customer Service Advisor, Financial Controller
B7: Notify Stakeholders | C7: The act of notifying all stakeholders of the transaction and related events. | E7: Transaction performed | F7: Agreement holder and all stakeholders notified | G7: Stakeholders are notified of transaction. | H7: Customer, Partner, Authorized Representative, Customer Service Advisor, Internal Stakeholder
B8: Verify Compliance | C8: The act of ensuring that processed transactions are recorded and retained in accordance with organization and regulatory policy. | E8: Transaction performed and all stakeholders notified | F8: All necessary transaction activities and compliance validation is complete | G8: A fully compliant transaction is complete. | H8: Customer, Partner, Authorized Representative, Customer Service Advisor, Channel Manager

Sheet Trade Financial Instrument
A1: Value Stream | B1: Value Stream Stage | C1: Description | D1: Value Proposition | E1: Entrance Criteria | F1: Exit Criteria | G1: Value Item | H1: Stakeholder(s)
A2: Trade Financial Instrument | C2: The act of executing a financial instrument trade, including clearing and settlement. | D2: Equitable, compliant trade of a financial instrument completed. | H2: Investor
B3: Initiate or Request Trade | C3: The act of making a request for trading a financial instrument. | E3: Need for trade determined/recognized | F3: Trade request submitted and received | G3: Requested trade is in progress. | H3: Investor, Broker-Dealer
B4: Select Accredited Broker-Dealer | C4: The act of determining and selecting which Broker-Dealer will execute the financial instrument trade. | E4: Trade request initiated | F4: Broker-Dealer selected | G4: Accredited and authorized Broker-Dealer has responsibility for the trade. | H4: Investor, Broker-Dealer
B5: Validate Trade Request | C5: The act of verifying if the requested financial instrument is suitable for the investor according to established investment goals. | E5: Trade request initiated | F5: Trade request validated | G5: Trade order ready for placement in the market. | H5: Registered Representative
B6: Obtain Trade Quotes | C6: The act of obtaining all available quotes for the requested instrument exchange. | E6: Trade request validated | F6: Trade order quotes received | G6: Trade order quotes obtained. | H6: Internal Firm, Broker-Dealer, Investment Manager
B7: Execute Trade Order | C7: The act of fulfilling (i.e., entering into an agreement with the counterparty to exchange the instrument) the trade order externally and matching to the investment trade agreements. | E7: Trade order submitted | F7: Trade order confirmed | G7: Trade order agreed/confirmed. | H7: Broker-Dealer, Security Trading Organization, Stock Exchange Broker, Market Maker
B8: Settle Trade | C8: The act of exchanging the agreed-upon financial instruments and verifying that the trade was done in accordance with all policies, regulations, and procedures. | E8: Trade order confirmed | F8: Trade settled between stakeholders (cleared) | G8: Requested trade is completed. | H8: Broker-Dealer, Investor, Trust Bank (Custodian)

Sheet Acquire Servicing Portfolio
A1: Value Stream | B1: Value Stream Stage | C1: Description | D1: Value Proposition | E1: Entrance Criteria | F1: Exit Criteria | G1: Value Item | H1: Stakeholder(s)
A2: Acquire Servicing Portfolio | C2: The act of acquiring the servicing rights for a portfolio of loans that have been serviced by another servicer. Ownership of the note stays with the owner of the loan. The security instrument and related legal documents may be assigned to the new servicer depending on note-owner contractual requirements. | D2: An institution acquires rights to service a number of financial accounts in exchange for fee-based income. | H2: Channel Manager, Product Manager, Financial Instrument Sales Advisor, Investment Manager, Agent
B3: Initiate Servicing Acquisition Inquiry | C3: A party looks to identify for buyers or sellers of rights to a specific servicing portfolio. | E3: A servicing portfolio for acquisition or sale is defined | F3: A buyer or seller is identified | G3: Interested parties are secured. | H3: Channel Manager, Product Manager, Financial Instrument Sales Advisor, Agent, Financial Instrument Sales Advisor, Investment Manager, Legal Counsel, Agent
B4: Conduct Servicing Portfolio Due Diligence | C4: Request documents or perform required activities necessary to assess the risk and meet compliance requirements of the transaction. | E4: Seller provides buyers required documentation | F4: Buyer and seller have positively completed due diligence review | G4: Buyer's and seller's due diligence requirements are met. | H4: Risk Officer, Financial Controller, Financial Instrument Sales Advisor, Financial Instrument Analyst, Investment Manager, Legal Counsel, Risk Officer
B5: Complete Servicing Portfolio Purchase Settlement | C5: Draft servicing agreement and close transaction. | E5: Agreement terms drafted | F5: Transaction settlement completed | G5: Transaction closed. | H5: Channel Manager, Product Manager, Financial Instrument Sales Advisor, Agent, Compliance/Risk Officer, Financial Instrument Sales Advisor, Financial Instrument Analyst, Investment Manager, Legal Counsel, Risk Officer, Trust Bank (Custodian)
B6: Acquire Serviced Portfolio | C6: Establish servicing portfolio assets at new institution. | E6: Assets to be serviced by new entity identified | F6: New servicing entity has incorporated assets into their processes and systems | G6: Asset established at new servicing entity. | H6: Financial Instrument Sales Advisor, Public Records Administrator, Quality Assurance Analyst, Trust Bank (Custodian), Operations Analyst
B7: Onboard Serviced Portfolio | C7: Set up and communicate appropriate financial account payment scheduling details and services. | E7: Financial accounts are established at servicing institution | F7: Financial accounts are being serviced | G7: Customers begin servicing financial accounts with new institution. | H7: Customer Service Advisor, Quality Assurance Analyst, Operations Analyst

Sheet Resolve Issue or Inquiry
A1: Value Stream | B1: Value Stream Stage | C1: Description | D1: Value Proposition | E1: Entrance Criteria | F1: Exit Criteria | G1: Value Item | H1: Stakeholder(s)
A2: Resolve Issue or Inquiry | C2: Activities necessary to track and resolve an issue or exception reported by a customer or other stakeholder. | D2: Issue or inquiry resolved to customer’s or initiator’s satisfaction. | H2: External Stakeholder or Internal Stakeholder
B3: Identify or report issue or inquiry | C3: The act of gathering all the known details of the exception/issue for the purpose of tracking and reporting through to resolution. | E3: An issue has been reported or an inquiry has been received | F3: Issue identified and recorded | G3: Issue accepted for review. | H3: Customer Service Representative
B4: Classify, Investigate, and Determine Cause | C4: The act of classifying and investigating the issue in order to determine the root cause. | E4: An identified and recorded case | F4: Root cause of the issue identified | G4: Root cause of the issue is identified. | H4: Customer Service Representative, Channel Manager, Product Manager
B5: Resolve | C5: The act of formulating and applying a course of action to correct or offset the effects of the issue. | E5: An issue with an identified cause | F5: Issue corrected | G5: Issue is resolved. | H5: Customer Service Representative, Channel Manager, Product Manager
B6: Notify Stakeholder(s) | C6: The act of notifying all stakeholders of the status and resolution of the issue. | E6: Corrected issue | F6: Stakeholders notified and satisfied | G6: All stakeholders notified of resolution. | H6: Initiating Stakeholder, Customer Service Representative
B7: Prevent Recurrence | C7: The act of making any changes to products and/or operational processes in order to prevent (or at least reduce the likelihood) of a recurrence of the issue or similar issues. | E7: Corrected issue and stakeholders notified and satisfied | F7: Corrective actions to prevent future occurrence | G7: Actions taken to ensure likelihood of issue recurring is reduced. | H7: Customer Service Representative, Channel Manager, Product Manager

Sheet Create Policy
A1: Value Stream | B1: Value Stream Stage | C1: Description | D1: Value Proposition | E1: Entrance Criteria | F1: Exit Criteria | G1: Value Item | H1: Stakeholder(s)
A2: Create Policy | C2: Activities involved in the end-to-end creation or update of policies that govern how the organization operates. | D2: Transparent, and consistent published governing policies for the benefit and protection of customers, shareholders, and the financial market. | H2: Regulator, Compliance/Risk Officer, Legal Counsel, Customer
B3: Initiate Policy | C3: The initiation of a policy creation or modification as a result of escalated concerns pertaining to the financial institution. | E3: Policy request initiated | F3: Policy request reviewed | G3: Policy request is initiated. | H3: Compliance/Risk Officer, Legal Counsel, Regulatory Auditor
B4: Evaluate Policy | C4: The collection and analysis of data from case law studies, consumers, financial institutions, existing policies, and other sources related to the policy being created or modified. | E4: Policy is initiated | F4: Policy is evaluated | G4: Policy data is validated and evaluated. | H4: Compliance/Risk Officer, Customer, Legal Counsel, Regulatory Auditor, Regulator
B5: Formulate Policy | C5: The drafting of a proposed policy or policy modification, collecting comments, editing, and finalizing the policy to submit for official voting. | E5: Policy data evaluation | F5: Policy is drafted | G5: Policy is formulated. | H5: Compliance/Risk Officer, Legal Counsel, Regulatory Auditor, Regulator
B6: Approve Policy | C6: The official review and legally binding vote by authorized persons (e.g., Compliance Risk Officer) to establish the creation or modification of a policy for a financial institution. | E6: Formulated policy | F6: Approved policy decision response | G6: Policy is approved. | H6: Compliance/Risk Officer, Legal Counsel
B7: Publish Policy | C7: The publication of the new or modified policy and resources for the financial institutions, consumers, and other stakeholders to understand and comply with. | E7: Approved policy | F7: Published policy | G7: Policy is published. | H7: Compliance/Risk Officer

Sheet Acquire Asset
A1: Value Stream | B1: Value Stream Stage | C1: Description | D1: Value Proposition | E1: Entrance Criteria | F1: Exit Criteria | G1: Value Item | H1: Stakeholder(s)
A2: Acquire Asset | C2: The end-to-end perspective of acquiring an asset, from initiating and approving the asset request, to sourcing and processing procurement orders and delivering the asset to the requester. | D2: Asset acquired. | H2: Asset Requester
B3: Request Asset | C3: The act of submitting a request for a new asset. | E3: Asset order initiated | F3: Asset order acknowledged | G3: Asset order requested. | H3: Asset Requester, Procurement Team Member
B4: Approve Order | C4: The act of validating that the asset request meets the procurement, financial, and business justification criteria. | E4: Asset order acknowledged | F4: Asset order approved | G4: Asset order validated. | H4: Asset Requester, Business Manager, Procurement Manager, Finance Manager
B5: Source Order | C5: The act of evaluating and selecting the supplier for the asset. | E5: Asset order approved | F5: Supplier selected | G5: Asset order sourced. | H5: Asset Requester, Procurement Manager, Procurement Team Member, Supplier
B6: Place Order | C6: The act of placing a procurement order to acquire the asset. | E6: Supplier selected | F6: Asset order placed | G6: Asset order processed. | H6: Procurement Team Member
B7: Receive Asset | C7: The act of fulfilling the order, receiving the asset, and accounting for the asset. | E7: Asset order placed | F7: Asset received | G7: Asset requester received asset. | H7: Supplier, Procurement Team Member, Asset Requester, Accountant

Sheet Conduct Audit
A1: Value Stream | B1: Value Stream Stage | C1: Description | D1: Value Proposition | E1: Entrance Criteria | F1: Exit Criteria | G1: Value Item | H1: Stakeholder(s)
A2: Conduct Audit | C2: The end-to-end perspective of determining the degree to which the organization is adhering to established policies and regulations. | D2: The company's compliance is evaluated and any corrective or disciplinary measures are identified. | H2: Chief Risk Officer, External Regulator
B3: Request Audit | C3: The act of requesting an audit. | E3: Audit request initiated | F3: Audit request received | G3: Audit request acknowledged. | H3: Chief Risk Officer, External Regulator
B4: Plan Audit | C4: The act of identifying the audit scope and execution plan. | E4: Audit request received | F4: Audit plan defined | G4: Audit planned. | H4: Auditor, Audited Business Team Members
B5: Gather Audit Information | C5: The act of discovering information pertinent to the audit scope. | E5: Audit plan defined | F5: Audit information gathered | G5: Audit information available. | H5: Auditor, Audited Business Team Members
B6: Analyze Audit Information | C6: The act of evaluating the information needed for the audit. | E6: Audit information gathered | F6: Audit information analyzed | G6: Audit information analysis completed. | H6: Auditor, Audited Business Team Members
B7: Document Audit Report | C7: The act of compiling the results of the audit. | E7: Audit information analyzed | F7: Audit report documented | G7: Audit report documented. | H7: Auditor
B8: Publish Audit Report | C8: The act of publishing the audit. | E8: Audit report documented | F8: Audit report published | G8: Audit requester received audit report. | H8: Auditor, Chief Risk Officer, External Regulator

Sheet Deliver Event
A1: Value Stream | B1: Value Stream Stage | C1: Description | D1: Value Proposition | E1: Entrance Criteria | F1: Exit Criteria | G1: Value Item | H1: Stakeholder(s)
A2: Deliver Meeting | C2: The end-to-end perspective of planning and executing a meeting. | D2: Meeting is held and the subject matter of the meeting is conducted. | H2: Asset Requester
B3: Initiate Meeting | C3: The act of conceiving, advancing, positing, or originating a meeting. | E3: Disposition and ability to deliver meeting | F3: Meeting concept proposed | G3: Meeting proposal. | H3: Asset Requester, Procurement Team Member
B4: Approve Meeting | C4: The act of defining the meeting and its subject matter, planning the meeting, budgeting and scheduling the meeting, identifying resources for the meeting, and approving the meeting. | E4: Meeting proposal | F4: Meeting plan finalized | G4: Approved meeting plan. | H4: Asset Requester, Business Manager, Procurement Manager, Finance Manager
B5: Prepare Meeting | C5: The act of securing resources, such as people, assets, or facilities for the meeting. | E5: Approved meeting plan | F5: Meeting resources, logistics secured | G5: Meeting resourced. | H5: Asset Requester, Procurement Manager, Procurement Team Member, Supplier
B6: Conduct Meeting | C6: The act of carrying out the activities defined in the meeting plan. | E6: Resources present, logistics finalized | F6: Meeting concluded | G6: Meeting delivered. | H6: Procurement Team Member
B7: Finalize Meeting | C7: The act of concluding the meeting, which may include activities such as communicating with stakeholders after a meeting, recording or memorializing the meeting subject matter, evaluating the outcomes of the meeting, paying for the meeting, or cleaning up after the meeting. | E7: Concluded meeting | F7: Post-meeting activities complete | G7: Meeting statistics, feedback, and outcomes collected. | H7: Supplier, Procurement Team Member, Asset Requester, Accountant

Sheet Deliver Program
A1: Value Stream | B1: Value Stream Stage | C1: Description | D1: Value Proposition | E1: Entrance Criteria | F1: Exit Criteria | G1: Value Item | H1: Stakeholder(s)
A2: Deliver Program | C2: The end-to-end perspective of planning and executing a program. | D2: Program outcome is delivered and the new/enhanced capabilities are transitioned to the sponsoring organization(s). | H2: Executive Sponsor
B3: Request Program | C3: The act of requesting the initiation of a program execution. | E3: Program request submitted | F3: Program request accepted | G3: Program request approved. | H3: Program Manager, Executive Sponsor
B4: Create Program Plan | C4: The act of defining the program plan, including program budget and schedule. | E4: Program request accepted | F4: Program plan created | G4: Program plan articulated. | H4: Program Manager, Executive Sponsor
B5: Approve Program Plan | C5: The act of approving the program plan. | E5: Program plan created | F5: Program plan approved | G5: Program plan approved. | H5: Executive Sponsor, Investment Committee
B6: Resource Program | C6: The act of securing program resources (e.g., money, people, assets). | E6: Program plan approved | F6: Program resources secured | G6: Program resourced. | H6: Program Manager
B7: Execute Program | C7: The act of performing the work defined in the program. | E7: Program resources secured | F7: Program execution completed | G7: Program benefits delivered. | H7: Program Manager, Program Team Member, Executive Sponsor
B8: Finalize Program | C8: The act of evaluating program metrics and transferring ownership to the sponsoring organization(s). | E8: Program execution completed | F8: Signed program acceptance | G8: Program work integrated into organization. | H8: Program Manager, Program Team Member, Executive Sponsor, Sponsoring Team Member

Sheet Deploy Asset
A1: Value Stream | B1: Value Stream Stage | C1: Description | D1: Value Proposition | E1: Entrance Criteria | F1: Exit Criteria | G1: Value Item | H1: Stakeholder(s)
A2: Deploy Asset | C2: The end-to-end perspective of evaluating, building, assembling, maintaining, and readying the asset for use to fill a need within an organization. | D2: Asset is made available and ready for use. | H2: Asset Requester, Partner, Asset Owner
B3: Receive Request | C3: The act of receiving the request for installation or maintenance of an asset. | E3: Asset request identified | F3: Asset request acknowledged | G3: Asset request accepted. | H3: Asset Requester, Asset Owner, Partner
B4: Validate Request | C4: The act of authenticating and verifying a request received for asset. | E4: Asset request accepted | F4: Asset request validated | G4: Asset request approved. | H4: Asset Request Evaluator
B5: Evaluate Asset | C5: The act of assessing performance or suitability of asset. | E5: Valid request, asset identified | F5: Asset performance and scope evaluated | G5: Asset scope of work approved. | H5: Asset Maintainer, Financial Analyst
B6: Configure Asset | C6: The act of initializing, setting up, creating, assembling, validating, or repairing asset in preparation for deployment. | E6: Asset scope of work identified | F6: Asset configured | G6: Asset ready for deployment. | H6: Asset Maintainer, Tester, Asset User
B7: Activate Asset | C7: The act of making the asset ready for use and closing the request. | E7: Asset ready for deployment | F7: Asset made available for use and request closed | G7: Asset activated for use. | H7: Asset Maintainer, Asset Requester, Asset User

Sheet Develop Human Resource Career
A1: Value Stream | B1: Value Stream Stage | C1: Description | D1: Value Proposition | E1: Entrance Criteria | F1: Exit Criteria | G1: Value Item | H1: Stakeholder(s)
A2: Develop Human Resource Career | C2: The end-to-end perspective of developing an individual's career, from performance assessment to skills and experience enhancement and individual redeployment. | D2: Individual is positioned for success, maximizes their contributions, and is committed to the company. | H2: Human Resource, Manager
B3: Initiate Career Evaluation | C3: The act of initiating the evaluation of an individual, triggered either by the individual or manager. | E3: Career evaluation request initiated | F3: Career evaluation request received | G3: Career evaluation request acknowledged. | H3: Human Resource, Manager
B4: Evaluate Human Resource | C4: The act of assessing the individual's skills and abilities, identifying potential career opportunities, and defining development plans to support those opportunities. | E4: Career evaluation request received | F4: Career development plan identified | G4: Career development plan defined. | H4: Employee, Manager, Human Resource Analyst
B5: Develop Human Resource | C5: The act of supporting the individual to execute his or her development plan and achieve the skills and experience required to meet desired career opportunities. | E5: Career development plan identified | F5: Career development plan executed | G5: Human resource skills and experience improved to match career opportunity. | H5: Employee, Manager, Human Resource Analyst, Training Team Member, Mentor
B6: Transition Human Resource | C6: The act of transitioning the individual into the desired career opportunity, along with adjustment of compensation and rewards as needed. | E6: Career development plan executed | F6: Career development achieved | G6: Human resource career developed. | H6: Employee, Manager, Human Resource Analyst

Sheet Disseminate Information
A1: Value Stream | B1: Value Stream Stage | C1: Description | D1: Value Proposition | E1: Entrance Criteria | F1: Exit Criteria | G1: Value Item | H1: Stakeholder(s)
A2: Disseminate Information | C2: The end-to-end perspective of requesting, creating, and delivering of information products to requester. | D2: Required information is available to requester. | H2: Requester
B3: Request Information | C3: The act of requesting information. | E3: Information request submitted | F3: Information request received and validated | G3: Information request communicated. | H3: Requester, Data Analyst
B4: Source Information | C4: The act of identifying the sources of information required to fulfill the request. | E4: Information request received and validated | F4: Information sources identified | G4: Information found. | H4: Data Analyst
B5: Process Information | C5: The act of creating the information product by extracting, transforming, loading, and aggregating the sources of information as needed, as well as validating its quality. | E5: Information sources identified | F5: Information prepared and validated | G5: Information created. | H5: Data Analyst
B6: Package Information | C6: The act of preparing information for consumption. | E6: Information prepared and validated | F6: Information packaged | G6: Information packaged. | H6: Data Analyst
B7: Deliver Information | C7: The act of delivering information to requester. | E7: Information packaged | F7: Information delivered to requester | G7: Information delivered. | H7: Data Analyst, Requester

Sheet Ensure Compliance
A1: Value Stream | B1: Value Stream Stage | C1: Description | D1: Value Proposition | E1: Entrance Criteria | F1: Exit Criteria | G1: Value Item | H1: Stakeholder(s)
A2: Ensure Compliance | C2: The end-to-end perspective of ensuring compliance with legislation and business-driven policies, from identifying compliance requirements to implementing controls, evaluating controls effectiveness, addressing compliance incidents, and reporting compliance as required. | D2: Company is compliant with both legislation and business-driven policies and avoids legal or reputation consequences. | H2: Chief Risk Officer, External Regulator
B3: Identify Compliance Requirements | C3: The act of identifying compliance requirements, either through legislation research or business policy creation. | E3: Compliance need identified | F3: Compliance requirements documented | G3: Compliance requirements acknowledged. | H3: Chief Risk Officer, External Regulator, Business Manager, Risk Manager
B4: Define Compliance Controls | C4: The act of analyzing compliance requirements and identifying safeguards and controls to be put in place to ensure compliance. | E4: Compliance requirements documented | F4: Compliance controls defined | G4: Compliance requirements analyzed. | H4: Risk Manager
B5: Implement Compliance Controls | C5: The act of implementing people, process, and technology changes, and required training to enable the predefined compliance controls. | E5: Compliance controls defined | F5: Compliance controls implemented | G5: Company's human resources and third parties are aware of the compliance controls and how they affect their processes and interactions. | H5: Risk Manager, Business Manager, Technology Manager, Human Resource, Customer, Partner
B6: Validate Compliance Controls | C6: The act of evaluating compliance controls' effectiveness and proactively manage compliance incidents, including disciplinary actions if required. | E6: Compliance controls implemented | F6: Compliance controls evaluated | G6: Compliance controls are optimal and compliance incidents are proactively addressed. | H6: Risk Manager, Business Manager, Human Resource, Customer, Partner
B7: Report Compliance | C7: The act of reporting compliance to the regulatory bodies and business management. | E7: Compliance controls evaluated | F7: Compliance reported | G7: Company is compliant with legislation and business-driven policies. | H7: Risk Manager, Chief Risk Officer, External Regulator

Sheet Execute Campaign
A1: Value Stream | B1: Value Stream Stage | C1: Description | D1: Value Proposition | E1: Entrance Criteria | F1: Exit Criteria | G1: Value Item | H1: Stakeholder(s)
A2: Execute Campaign | C2: The end-to-end perspective of executing a campaign, from identifying the need for a campaign, to planning, designing, implementing, and measuring the effectiveness of the campaign. | D2: The campaign message has been delivered to the campaign targets, the effectiveness of the campaign results have been analyzed, and potential future optimization plans have been identified. | H2: Campaign Requester
B3: Request Campaign | C3: The act of submitting a request for a campaign. | E3: Campaign need identified | F3: Campaign request received | G3: Campaign request acknowledged. | H3: Campaign Requester, Product Manager
B4: Plan Campaign | C4: The act of defining a campaign plan, including campaign targets and message, delivery channels, implementation schedule, success criteria, and required campaign budget and resources. | E4: Campaign request received | F4: Campaign plan approved | G4: Campaign plans defined. | H4: Campaign Requester, Product Manager
B5: Design Campaign | C5: The act of defining campaign collateral, including target specific messaging and graphic designs for each delivery channel. | E5: Campaign plan approved | F5: Campaign execution approved | G5: Campaign execution designed. | H5: Campaign Requester, Campaign Resource
B6: Implement Campaign | C6: The act of delivering campaign content as planned. | E6: Campaign execution approved | F6: Campaign delivered to targets | G6: Campaign message received by campaign targets. | H6: Campaign Resource, Campaign Target
B7: Evaluate Campaign | C7: The act of measuring effectiveness of a campaign and identify possible optimizations for future execution. | E7: Campaign delivered to targets | F7: Campaign results identified and analyzed | G7: Campaign effectiveness measured and optimization plans identified. | H7: Campaign Requester, Product Manager

Sheet Onboard Human Resource
A1: Value Stream | B1: Value Stream Stage | C1: Description | D1: Value Proposition | E1: Entrance Criteria | F1: Exit Criteria | G1: Value Item | H1: Stakeholder(s)
A2: Onboard Human Resource | C2: The end-to-end perspective of identifying, exploring, and selecting an individual to fill a need within an organization. | D2: A productive individual fills the identified need and is ready to contribute. | H2: Hiring Manager
B3: Request Position | C3: The act of submitting a recruitment requisition for a vacancy required to perform work for the organization. | E3: Recruitment requisition initiated | F3: Recruitment requisition acknowledged | G3: Recruitment requisition opened. | H3: Hiring Manager, Recruiter
B4: Validate Position | C4: The act of verifying that the recruitment requisition's financial and business justification criteria are acceptable. | E4: Recruitment requisition acknowledged | F4: Position validated | G4: Position opened. | H4: Hiring Manager, Recruiter
B5: Source Individuals | C5: The act of finding individuals who may qualify for the open position and validating their interest. | E5: Position validated | F5: Candidate list established | G5: Potential matches for open position identified. | H5: Hiring Manager, Recruiter, Candidate(s)
B6: Evaluate Individuals | C6: The act of assessing the potential candidates against the open position requirements and extending an offer to the most qualified individual. | E6: Candidate list established | F6: Offer extended | G6: Match for open position identified. | H6: Hiring Manager, Recruiter, Candidate(s)
B7: Finalize Acceptance | C7: The act of negotiating the employment agreement terms and conditions. | E7: Offer extended | F7: Offer accepted/rejected | G7: Commitment from individual confirmed. | H7: Hiring Manager, Recruiter, Human Resource
B8: Onboard Individual | C8: The act of bringing an individual into the organization and providing necessary training and resources for him or her to effectively start contributing. | E8: Offer accepted | F8: Onboarding completed | G8: Individual is contributing. | H8: Hiring Manager, Recruiter, Human Resource

Sheet Optimize Investments
A1: Value Stream | B1: Value Stream Stage | C1: Description | D1: Value Proposition | E1: Entrance Criteria | F1: Exit Criteria | G1: Value Item | H1: Stakeholder(s)
A2: Optimize Investments | C2: The end-to-end perspective of deciding where to make investments, based on the understanding of the enterprise's goals, strategy, current positions, and external forces. | D2: Company investments are optimal. | H2: Chief Executive Officer, Board
B3: Initiate Investment Review | C3: The act of understanding the strategy and goals of the enterprise. | E3: Investment review request initiated | F3: Investment review request received | G3: Investment review request acknowledged. | H3: Chief Executive Officer, Board, Chief Financial Officer
B4: Assess Current Position | C4: The act of gathering and analyzing all relevant information related to transformation of financial and customer goals and objectives. | E4: Investment review request received | F4: Company current position analyzed | G4: Investment needs identified. | H4: Chief Financial Officer, Treasurer
B5: Investigate Investment Options | C5: The act of recognizing, designing, evaluating, and prioritizing actions in accordance with strategy, cause-and-effect linkages, and policies and regulations. | E5: Company current position analyzed | F5: Potential investment options identified | G5: Potential investments identified. | H5: Chief Financial Officer, Treasurer, Financial Analyst
B6: Select Investment Options | C6: The act of selecting a course of action based on assessment of options. | E6: Potential investment options identified | F6: Investment options identified | G6: Optimal investments identified. | H6: Chief Financial Officer, Treasurer, Chief Executive Officer, Board
B7: Execute Investment Options | C7: The act of putting an investment plan in motion. | E7: Investment options identified | F7: Investment options executed | G7: Optimal investments in place. | H7: Chief Financial Officer

Sheet Report Financials
A1: Value Stream | B1: Value Stream Stage | C1: Description | D1: Value Proposition | E1: Entrance Criteria | F1: Exit Criteria | G1: Value Item | H1: Stakeholder(s)
A2: Report Financials | C2: The end-to-end perspective of preparing, approving, and releasing external financial statements that disclose an organization's financial status to management, investors, and the government. | D2: Company is compliant with financial regulations and its financial standing is communicated to management, investors, and government. | H2: Chief Financial Officer, Board
B3: Initiate Financial Statements Generation | C3: The act of initiating the generation of financials statements, either on request or after the financial period closure. | E3: Financial statements request identified | F3: Financial statements request initiated | G3: Financial statement requests acknowledged. | H3: Chief Financial Officer, Board
B4: Prepare Financial Statements | C4: The act of generating the financial statements (balance sheet, income statement, cash flow statement, shareholders' equity statement) and annotating them with the summarized findings. | E4: Financial statement request initiated | F4: Financial statements generated and annotated | G4: Financial statements prepared. | H4: Finance Controller
B5: Approve Financial Statements | C5: The act of reviewing and approving the financial statements and associated notes. | E5: Financial statements generated and annotated | F5: Financial statements approved | G5: Financial statements approved. | H5: Chief Financial Officer, Chief Executive Officer, Management, Board of Directors
B6: Release Financial Statements | C6: The act of organizing and facilitating press releases and conference calls regarding quarterly earnings and related information, releasing quarterly and annual reports to investors, and posting financial information on the corporation's website. | E6: Financial statements approved | F6: Financial statements communicated to management and investors | G6: Management and investors are aware of the company financial standings. | H6: Chief Financial Officer, Finance Controller, Management, Investors
B7: File Financial Statements | C7: The act of filing financial reports to governmental agencies including quarterly and annual reports to the Securities and Exchange Commission (SEC). | E7: Financial statements communicated to management and investors | F7: Financial statements submitted to regulators | G7: Company compliant with financial regulations. | H7: Chief Financial Officer, Regulatory Bodies

Sheet Settle Accounts
A1: Value Stream | B1: Value Stream Stage | C1: Description | D1: Value Proposition | E1: Entrance Criteria | F1: Exit Criteria | G1: Value Item | H1: Stakeholder(s)
A2: Settle Accounts | C2: The end-to-end perspective enabling the bi-directional exchange of payments between an organization and a customer, partner, or human resource. | D2: Finalizing the payment exchange for goods or services rendered or planned to be rendered. | H2: Customer, Human Resource, Organization, Partner
B3: Request Payment | C3: The act of sending or receiving the request for payment. | E3: Payment requirement | F3: Payment notice received | G3: Payment request received. | H3: Customer, Human Resource, Organization, Partner
B4: Validate Payment Request | C4: The act of reconciling the request for payment with the goods or services. | E4: Received notice of payment requirement | F4: Payment request validated | G4: Payment request validated. | H4: Customer, Human Resource, Organization, Partner
B5: Exchange Funds | C5: The act of transferring funds to payment for goods or services. | E5: Payment request validated | F5: Payment transaction completed | G5: Payment made. | H5: Customer, Human Resource, Organization, Partner
B6: Update Financial Accounts | C6: The act of recording the exchange of funds in financial accounts. | E6: Payment transaction completed | F6: Account records updated | G6: Accounts reconciled. | H6: Customer, Human Resource, Organization, Partner

Sheet Onboard Partner
A1: Value Stream | B1: Value Stream Stage | C1: Description | D1: Value Proposition | E1: Entrance Criteria | F1: Exit Criteria | G1: Value Item | H1: Stakeholder(s)
A2: Onboard Partner | C2: The end-to-end perspective of identifying and commencing business with other organizations for mutual benefit. | D2: The delivery of goods and/or services that the organization chooses to deliver through others. | H2: Partnering Officer, Partner
B3: Identify Need | C3: The act of defining the business requirements for goods and services that cannot be obtained internally. | E3: Problem or opportunity defined | F3: Need identified | G3: Identified need. | H3: Partnering Officer
B4: Vet Potential Partner | C4: The act of validating that the potential partner is capable of delivering on the value proposition and meets ethical guidelines. | E4: Need and potential partner identified | F4: Partner vetted | G4: Vetted partner. | H4: Partnering Officer, Partner
B5: Negotiate Terms | C5: The act of reviewing and negotiating the terms of the contract including such things as cost, scope, and length of engagement. | E5: Partner vetted | F5: Finalized terms | G5: Terms finalized. | H5: Partnering Officer, Partner, Legal Officer
B6: Formalize Agreement | C6: The act of reaching final agreement on the terms of the contract. | E6: Finalized terms | F6: Formalized agreement | G6: Agreement formalized. | H6: Partnering Officer, Partner, Legal Officer
B7: Induct Partner | C7: The act of onboarding the partner to make them familiar with how they are expected to engage with the organization. | E7: Formalized agreement | F7: Onboarded partner | G7: Partner onboarded. | H7: Partnering Officer, Partner
